pensive/__init__.py
pensive-0.0.0.dist-info/METADATA
pensive-0.0.0.dist-info/WHEEL
pensive-0.0.0.dist-info/top_level.txt
pensive-0.0.0.dist-info/zip-safe
pensive-0.0.0.dist-info/RECORD
