Metadata-Version: 2.1
Name: pensive
Version: 0.0.0
Summary: Python library for creating and drawing graphs and taking advantage of graph properties
Home-page: https://github.com/idin/pensive
Author: Idin
Author-email: py@idin.ca
License: MIT
Keywords: graph
Platform: UNKNOWN
Classifier: Development Status :: 3 - Alpha
Classifier: Intended Audience :: Developers
Classifier: License :: OSI Approved :: MIT License
Classifier: Programming Language :: Python :: 3 :: Only
Classifier: Programming Language :: Python :: 3.6
Classifier: Programming Language :: Python :: 3.7
Classifier: Topic :: Software Development :: Libraries :: Python Modules
Requires-Python: ~=3.6
